MANIFEST.in
README.rst
setup.py
mezzanine_instagram_quickphotos.egg-info/PKG-INFO
mezzanine_instagram_quickphotos.egg-info/SOURCES.txt
mezzanine_instagram_quickphotos.egg-info/dependency_links.txt
mezzanine_instagram_quickphotos.egg-info/pbr.json
mezzanine_instagram_quickphotos.egg-info/requires.txt
mezzanine_instagram_quickphotos.egg-info/top_level.txt
mezzanine_quickphotos/__init__.py
mezzanine_quickphotos/admin.py
mezzanine_quickphotos/apps.py
mezzanine_quickphotos/defaults.py
mezzanine_quickphotos/models.py
mezzanine_quickphotos/tests.py
mezzanine_quickphotos/utils.py
mezzanine_quickphotos/views.py
mezzanine_quickphotos/management/__init__.py
mezzanine_quickphotos/management/commands/__init__.py
mezzanine_quickphotos/management/commands/instagram_auth.py
mezzanine_quickphotos/management/commands/instagram_likes.py
mezzanine_quickphotos/management/commands/instagram_update.py
mezzanine_quickphotos/migrations/0001_initial.py
mezzanine_quickphotos/migrations/__init__.py
mezzanine_quickphotos/templatetags/__init__.py
mezzanine_quickphotos/templatetags/quickphotos_tags.py