Metadata-Version: 1.1
Name: mezzanine-instagram-quickphotos
Version: 0.0.2
Summary: Latest Photos from Instagram for Mezzanine
Home-page: https://github.com/kmlebedev/mezzanine-instagram-quickphotos
Author: Konstantin Lebedev
Author-email: lebedev.k.m@gmail.com
License: BSD
Platform: any
Classifier: Environment :: Web Environment
Classifier: Framework :: Django
Classifier: Framework :: Django :: 1.10
Classifier: License :: OSI Approved :: BSD License
Classifier: Operating System :: OS Independent
Classifier: Programming Language :: Python
Classifier: Programming Language :: Python :: 2
Classifier: Programming Language :: Python :: 2.7
Classifier: Programming Language :: Python :: 3
Classifier: Programming Language :: Python :: 3.3
Classifier: Programming Language :: Python :: 3.4
Classifier: Programming Language :: Python :: 3.5
